plone.transformchain-3.0.2-py3.13-nspkg.pth
plone/transformchain/__init__.py
plone/transformchain/configure.zcml
plone/transformchain/events.py
plone/transformchain/interfaces.py
plone/transformchain/tests.py
plone/transformchain/transformer.py
plone/transformchain/zpublisher.py
plone_transformchain-3.0.2.dist-info/METADATA
plone_transformchain-3.0.2.dist-info/WHEEL
plone_transformchain-3.0.2.dist-info/namespace_packages.txt
plone_transformchain-3.0.2.dist-info/top_level.txt
plone_transformchain-3.0.2.dist-info/RECORD
