Metadata-Version: 2.4
Name: plone.transformchain
Version: 3.0.2
Summary: Hook into repoze.zope2 that allows third party packages to register a sequence of hooks that will be allowed to modify the response before it is returned to the browser
Home-page: https://pypi.org/project/plone.transformchain
Author: Martin Aspeli
Author-email: optilude@gmail.com
License: BSD
Keywords: zope2 repoze transform
Classifier: Development Status :: 5 - Production/Stable
Classifier: Framework :: Plone
Classifier: Framework :: Plone :: 6.0
Classifier: Framework :: Plone :: Core
Classifier: License :: OSI Approved :: BSD License
Classifier: Programming Language :: Python
Classifier: Programming Language :: Python :: 3.8
Classifier: Programming Language :: Python :: 3.9
Classifier: Programming Language :: Python :: 3.10
Classifier: Programming Language :: Python :: 3.11
Classifier: Topic :: Software Development :: Libraries :: Python Modules
Requires-Python: >=3.8
Requires-Dist: setuptools
Requires-Dist: Zope
Provides-Extra: test
Requires-Dist: plone.testing[zca]; extra == "test"
Dynamic: author
Dynamic: author-email
Dynamic: classifier
Dynamic: description
Dynamic: home-page
Dynamic: keywords
Dynamic: license
Dynamic: provides-extra
Dynamic: requires-dist
Dynamic: requires-python
Dynamic: summary
